bhad/__init__.py
bhad/explainer.py
bhad/model.py
bhad/utils.py
bhad-0.2.9.1.dist-info/licenses/LICENSE
bhad-0.2.9.1.dist-info/METADATA
bhad-0.2.9.1.dist-info/WHEEL
bhad-0.2.9.1.dist-info/top_level.txt
bhad-0.2.9.1.dist-info/RECORD
