Metadata-Version: 2.4
Name: bhad
Version: 0.2.9.1
Summary: Bayesian Histogram-based Anomaly Detection
Author: Alexander Vosseler
Maintainer: Alexander Vosseler
Project-URL: homepage, https://github.com/AVoss84/bhad
Project-URL: repository, https://github.com/AVoss84/bhad
Project-URL: issues, https://github.com/AVoss84/bhad/issues
Keywords: bayesian-inference,anomaly-detection,unsupervised-learning,explainability
Classifier: Programming Language :: Python :: 3
Classifier: License :: OSI Approved :: MIT License
Classifier: Operating System :: OS Independent
Requires-Python: >=3.12
License-File: LICENSE
Requires-Dist: pandas>=1.5
Requires-Dist: scikit-learn>=1.3
Requires-Dist: matplotlib>=3.0
Requires-Dist: scipy<1.13,>=1.9
Requires-Dist: statsmodels>=0.14
Requires-Dist: tqdm>=4.0
Dynamic: license-file
